{
  "reported_pmids": {
    "42265997": {
      "title": "2026 AHA/ACC/ADA/ASN Guideline for the Prevention, Detection, Evaluation, and Management of Cardiovascular-Kidney-Metabolic Syndrome: A Report of the American College of Cardiology/American Heart Association Joint Committee on Clinical Practice Guidelines.",
      "reported_at": "2026-06-13T13:21:05.393331"
    },
    "42258629": {
      "title": "The emerging role of coronary computed tomography for prevention of cardiovascular disease in asymptomatic individuals.",
      "reported_at": "2026-06-13T13:21:05.393331"
    },
    "42263012": {
      "title": "Use of Predicted Risk and Expected Benefit to Guide Decision-Making in Cardiovascular-Kidney-Metabolic Syndrome for the Primary Prevention of Cardiovascular Disease: A Scientific Statement From the American Heart Association and American College of Cardiology.",
      "reported_at": "2026-06-13T13:21:05.393331"
    },
    "42263147": {
      "title": "Use of Predicted Risk and Expected Benefit to Guide Decision-Making in Cardiovascular-Kidney-Metabolic Syndrome for the Primary Prevention of Cardiovascular Disease: A Scientific Statement From the American Heart Association and American College of Cardiology.",
      "reported_at": "2026-06-13T13:21:05.393331"
    },
    "42263157": {
      "title": "2026 AHA/ACC/ADA/ASN Guideline for the Prevention, Detection, Evaluation, and Management of Cardiovascular-Kidney-Metabolic Syndrome: A Report of the American College of Cardiology/American Heart Association Joint Committee on Clinical Practice Guidelines.",
      "reported_at": "2026-06-13T13:21:05.393331"
    },
    "42250575": {
      "title": "Efficacy and safety of retatrutide, a GIP, GLP-1, and glucagon receptor agonist, in people with type 2 diabetes and inadequate glycaemic control with diet and exercise (TRANSCEND-T2D-1): a double-blind, randomised, phase 3 trial.",
      "reported_at": "2026-06-13T13:29:07.031288"
    },
    "42242268": {
      "title": "Atrasentan in patients with IgA nephropathy (ALIGN): final 2·5-year results from a randomised, double-blind, placebo-controlled, phase 3 trial.",
      "reported_at": "2026-06-13T13:29:07.031288"
    },
    "42274082": {
      "title": "Assessing Organizational Readiness for Just Culture in Health Care.",
      "reported_at": "2026-06-13T13:29:07.031288"
    },
    "42119587": {
      "title": "Tirzepatide for maintenance of bodyweight reduction in people with obesity in the USA (SURMOUNT-MAINTAIN): a multicentre, double-blind, randomised, placebo-controlled trial.",
      "reported_at": "2026-06-13T13:29:07.031288"
    },
    "41911016": {
      "title": "Intravascular Ultrasound-Guided or Angiography-Guided Complex High-Risk PCI.",
      "reported_at": "2026-06-13T13:29:07.031288"
    },
    "42267500": {
      "title": "The role of emerging technology in expanding regional anesthesia education and patient access.",
      "reported_at": "2026-06-14T10:33:58.361303"
    },
    "42295178": {
      "title": "Major Adverse Cardiovascular Events After Hip Fracture Surgery with Remimazolam or Propofol Total Intravenous Anesthesia: A Retrospective Cohort Study Emulating a Target Trial.",
      "reported_at": "2026-06-15T17:39:59.554020"
    },
    "41944587": {
      "title": "Gabapentin and Opioid Prescribing Trends among Adolescents Undergoing Common Procedures: A National Retrospective Cohort Study.",
      "reported_at": "2026-06-15T17:39:59.554020"
    },
    "42268604": {
      "title": "Superficial Cervical Plexus Block and Quality of Recovery after Thyroidectomy: A Randomized Clinical Trial.",
      "reported_at": "2026-06-15T17:39:59.554020"
    },
    "41944592": {
      "title": "Pain Trajectories after Orthopedic Surgery in Older Adults: An Analysis of Predictors and Associations with Postoperative Outcomes.",
      "reported_at": "2026-06-15T17:39:59.554020"
    },
    "42284616": {
      "title": "The Influence of Depth of Anesthesia on Motor Evoked Potentials Monitoring During Spinal Surgery in Youth: A Single-Center Prospective Study (SCOL Study).",
      "reported_at": "2026-06-15T17:39:59.554020"
    },
    "42270151": {
      "title": "National patterns and variation in regional anesthesia use for shoulder, hip, knee, and ankle arthroplasty: a National Inpatient Sample analysis.",
      "reported_at": "2026-06-16T16:11:38.815522"
    },
    "42269556": {
      "title": "Effects of deep parasternal intercostal plane block on opioid consumption and pain after cardiac surgery: a meta-analysis of randomized controlled trials with meta-regression and trial sequential analysis.",
      "reported_at": "2026-06-16T16:11:38.815522"
    },
    "42268736": {
      "title": "Large-Scale Evaluation of Five Large Language Models in Anesthesia Decision-Making for Hip Fracture Surgery.",
      "reported_at": "2026-06-16T16:11:38.815522"
    },
    "42270529": {
      "title": "Perioperative discontinuation of SGLT2-inhibitors and cardiac complications after noncardiac surgery: secondary analysis of two prospective observational cohort studies.",
      "reported_at": "2026-06-17T12:57:54.079790"
    },
    "42287860": {
      "title": "Effect of midodrine on orthostatic intolerance after hip and knee arthroplasty: A randomized controlled trial (the MObILE study).",
      "reported_at": "2026-06-17T12:57:54.079790"
    },
    "42294779": {
      "title": "What a pain! The elusive management of an individual patient with SCN9A sodium channelopathy in the perioperative setting.",
      "reported_at": "2026-06-17T12:57:54.079790"
    },
    "42274020": {
      "title": "Disability after non-cardiac surgery - patient-centred outcomes and resource utilisation after non-cardiac surgery (PACORUS): a prospective multicentre cohort study.",
      "reported_at": "2026-06-17T12:57:54.079790"
    },
    "42150044": {
      "title": "Prehospital Resuscitation with Type O Whole Blood for Trauma and Hemorrhage.",
      "reported_at": "2026-06-18T12:00:52.679475"
    },
    "42090639": {
      "title": "Effect of Weight-based versus Absolute Norepinephrine Dosing on Mortality Risk in Obese Patients with Septic Shock: An Observational, Multicohort, Retrospective Study.",
      "reported_at": "2026-06-18T12:00:52.679475"
    },
    "42301312": {
      "title": "Current knowledge and challenges of sepsis-associated encephalopathy.",
      "reported_at": "2026-06-18T12:00:52.679475"
    },
    "42285119": {
      "title": "Postpartum haemorrhage: epidemiology, consequences, and missed opportunities.",
      "reported_at": "2026-06-18T12:00:52.679475"
    },
    "42274006": {
      "title": "Vasopressors or Fluids in Early Septic Shock.",
      "reported_at": "2026-06-18T12:00:52.679475"
    },
    "42259337": {
      "title": "Elecoglipron, an oral small molecule GLP-1 receptor agonist in adults with obesity or overweight (VISTA): a multicentre, phase 2, randomised, placebo-controlled clinical trial.",
      "reported_at": "2026-06-20T08:37:21.622583"
    },
    "42259343": {
      "title": "Elecoglipron, an oral small molecule GLP-1 receptor agonist in adults with type 2 diabetes (SOLSTICE): a multicentre, phase 2b, randomised, placebo-controlled trial.",
      "reported_at": "2026-06-20T08:37:21.622583"
    },
    "42305067": {
      "title": "Reducing High-risk Meal Tray Delivery Errors in Inpatient Rehabilitation Through Wristband Scanning and Interdisciplinary Workflow Optimization.",
      "reported_at": "2026-06-20T08:37:21.622583"
    },
    "41841706": {
      "title": "Prehospital Whole Blood in Traumatic Hemorrhage - A Randomized Controlled Trial.",
      "reported_at": "2026-06-20T08:37:21.622583"
    },
    "42217458": {
      "title": "Tafasitamab plus lenalidomide and R-CHOP versus R-CHOP for first-line treatment of patients with high-risk diffuse large B-cell lymphoma (frontMIND): a global, phase 3, randomised, double-blind, placebo-controlled trial.",
      "reported_at": "2026-06-20T08:37:21.622583"
    },
    "42309961": {
      "title": "Culture, power and practice: Critical discourse analysis of workplace-based assessments in hierarchical postgraduate medical education.",
      "reported_at": "2026-06-21T10:54:49.713957"
    },
    "42309548": {
      "title": "Comparison of intrathecal morphine versus thoracic paravertebral block for video-assisted thoracoscopic surgery: a randomized non-inferiority trial.",
      "reported_at": "2026-06-22T16:16:09.065380"
    },
    "42294965": {
      "title": "Determinants of Delayed Recovery of Consciousness After Analgosedation Discontinuation in the ICU: Insights From Patients With COVID-19 Hypoxemic Respiratory Failure.",
      "reported_at": "2026-06-22T16:16:09.065380"
    },
    "42295435": {
      "title": "Predictive value of ultrasound-measured tongue base thickness for upper airway obstruction during monitored anesthesia care: a single-center prospective observational study.",
      "reported_at": "2026-06-22T16:16:09.065380"
    },
    "42329746": {
      "title": "Enhanced recovery pathways for patients with chronic pain: beyond standard protocols - a narrative review.",
      "reported_at": "2026-06-23T10:48:55.213525"
    },
    "42301200": {
      "title": "Regional anaesthesia and analgesia in surgical patients with chronic preoperative pain: mechanisms, evidence, and clinical implications.",
      "reported_at": "2026-06-23T10:48:55.213525"
    },
    "42317096": {
      "title": "Wide-awake local anesthesia no tourniquet (WALANT) versus brachial plexus block for upper extremity surgery: a systematic review and meta-analysis.",
      "reported_at": "2026-06-23T10:48:55.213525"
    },
    "42304663": {
      "title": "The analgesic efficacy of intrathecal morphine compared to peripheral regional analgesia in total hip arthroplasty: A systematic review and meta-analysis.",
      "reported_at": "2026-06-23T10:48:55.213525"
    },
    "42313662": {
      "title": "Novel technologies and innovations in postoperative follow-up after regional anesthesia.",
      "reported_at": "2026-06-23T10:48:55.213525"
    },
    "41911318": {
      "title": "Intraoperative Hemodynamic Management during Liver Transplantation and Postoperative Morbidity: A Multicenter Cohort Study.",
      "reported_at": "2026-06-24T10:28:53.167010"
    },
    "42315625": {
      "title": "How to optimize brain perfusion and prevent cerebral complications during extracorporeal life support.",
      "reported_at": "2026-06-25T10:00:32.644001"
    },
    "42332337": {
      "title": "Association between lactate clearance rate and 28-day mortality in patients with sepsis: a retrospective cohort study and exploration of an optimal lactate clearance as an endpoint of resuscitation.",
      "reported_at": "2026-06-25T10:00:32.644001"
    },
    "42329250": {
      "title": "PEEP and alveolar recruitment after 60 years of acute respiratory distress syndrome.",
      "reported_at": "2026-06-25T10:00:32.644001"
    },
    "42312687": {
      "title": "Association Between Emergency Department-to-ICU Transfer Time and Hospital Mortality Across ICU Admission Diagnoses: A Post Hoc Subgroup Analysis.",
      "reported_at": "2026-06-25T10:00:32.644001"
    },
    "42339875": {
      "title": "Ethical Implications of the Slow Code: A Systematic Review of Ethics of Slow Codes in U.S. Hospitals.",
      "reported_at": "2026-06-25T10:00:32.644001"
    },
    "42350329": {
      "title": "Clinical Risk Management and Patient-safety Research: A Large-scale Bibliometric Mapping of the Field and Its Emerging Directions (Master vs. 2021-2025).",
      "reported_at": "2026-06-27T08:12:04.328289"
    },
    "42341301": {
      "title": "A Pragmatic Trial of a 6-Month Strategy for Rifampicin-Resistant Tuberculosis.",
      "reported_at": "2026-06-27T08:12:04.328289"
    },
    "42207501": {
      "title": "Adverse Effects and Treatment Discontinuation of Blood Pressure-Lowering Drugs and Combinations: A Network Meta-Analysis.",
      "reported_at": "2026-06-27T08:12:04.328289"
    },
    "42206582": {
      "title": "Phase 3 Results of Bepirovirsen Treatment for Chronic Hepatitis B Virus Infection.",
      "reported_at": "2026-06-27T08:12:04.328289"
    },
    "42041224": {
      "title": "Pulsed Field Ablation as Initial Therapy for Persistent Atrial Fibrillation.",
      "reported_at": "2026-06-27T08:12:04.328289"
    },
    "42350172": {
      "title": "Eye-tracking technology applied to regional anaesthesia task performance, safety and skill acquisition: a scoping review.",
      "reported_at": "2026-06-28T08:36:04.517433"
    },
    "42324172": {
      "title": "With great power comes great responsibility: How narrow conceptions of validity in high-stakes testing undermine competence.",
      "reported_at": "2026-06-28T08:36:04.517433"
    },
    "42228455": {
      "title": "Crisis resource management in nonoperating room anesthesia.",
      "reported_at": "2026-06-28T08:36:04.517433"
    },
    "42362357": {
      "title": "New persistent opioid use following surgery among opioid-naïve patients in the USA: a systematic review and meta-analysis of observational studies.",
      "reported_at": "2026-06-29T13:18:53.395803"
    },
    "42363899": {
      "title": "Anesthesia Care, Complications, and Airway Management for Patients With Spinal Muscular Atrophy: A Retrospective Chart Review From a Quaternary Children's Hospital.",
      "reported_at": "2026-06-29T13:18:53.395803"
    },
    "42350062": {
      "title": "Analgesic efficacy of locoregional anesthesia techniques in cardiac surgery: a systematic review and network meta-analysis of randomized trials.",
      "reported_at": "2026-06-29T13:18:53.395803"
    },
    "42207626": {
      "title": "Adult Male Hypogonadism: A Review.",
      "reported_at": "2026-06-29T13:18:53.395803"
    },
    "42336494": {
      "title": "Impact of continuous serratus plane analgesia on quality of recovery after video-assisted thoracic surgery: a prospective double-blind, randomized, placebo-controlled trial.",
      "reported_at": "2026-06-30T10:43:09.365755"
    },
    "42341401": {
      "title": "Minimum effective volume of the pericapsular nerve group (PENG) block in association with a standardized obturator nerve block for analgesia in hip osteoarthritis: An up-and-down study.",
      "reported_at": "2026-06-30T10:43:09.365755"
    },
    "42362356": {
      "title": "Sensory innervation of the knee joint: a narrative review of articular branch mapping and sensory receptor distribution.",
      "reported_at": "2026-06-30T10:43:09.365755"
    },
    "42337915": {
      "title": "Effects of single-injection vs. continuous brachial plexus blocks for shoulder surgeries on patient-reported outcomes: a systematic review and meta-analysis with trial sequential analysis of randomised controlled trials.",
      "reported_at": "2026-06-30T10:43:09.365755"
    },
    "41574413": {
      "title": "Association between postoperative delirium in the postanaesthesia care unit and subsequent ward delirium: A retrospective cohort study.",
      "reported_at": "2026-07-01T10:56:51.785244"
    },
    "41506973": {
      "title": "Preoperative beta blocker use and postoperative ischaemic stroke risk in noncardiac surgery: a multicentre retrospective cohort study.",
      "reported_at": "2026-07-01T10:56:51.785244"
    },
    "42304626": {
      "title": "Remifentanil Versus Rocuronium for Optimising Video Laryngoscopy Assisted Tracheal Intubation-The ROCVIDEO Trial Protocol.",
      "reported_at": "2026-07-01T10:56:51.785244"
    },
    "42191528": {
      "title": "Withholding or continuing glucose-lowering drugs for elective surgery in patients with type 2 diabetes mellitus: a secondary analysis of the MOPED international, prospective, observational study.",
      "reported_at": "2026-07-01T10:56:51.785244"
    },
    "42171481": {
      "title": "Digital Versus in-Person Pre-Anaesthetic Assessment and Postoperative Outcomes in Low-Risk Patients: A Protocol for a Single-Centre Cohort Study.",
      "reported_at": "2026-07-01T10:56:51.785244"
    },
    "42138515": {
      "title": "Prognostic Factors Associated With Mortality Among Patients With Necrotizing Soft-Tissue Infection: A Systematic Review and Meta-Analysis.",
      "reported_at": "2026-07-02T08:37:41.153705"
    },
    "42371000": {
      "title": "ECMO for patients with obesity: evidence and practice.",
      "reported_at": "2026-07-02T08:37:41.153705"
    },
    "42377463": {
      "title": "Effects of a clinical metagenomics intervention on clinical outcomes, healthcare costs, and health-related quality of life in patients with sepsis or septic shock: results of the randomized-controlled DigiSep trial.",
      "reported_at": "2026-07-02T08:37:41.153705"
    },
    "42289350": {
      "title": "COVID-19 Mortality in Swedish Intensive Care Units: A Multicenter Survival Analysis.",
      "reported_at": "2026-07-02T08:37:41.153705"
    },
    "42207935": {
      "title": "Technology-Enhanced Strategies to Optimize Positive End-Expiratory Pressure in Patients Receiving Invasive Mechanical Ventilation: A Systematic Review and Meta-Analysis.",
      "reported_at": "2026-07-02T08:37:41.153705"
    },
    "41134317": {
      "title": "Intravenous Lidocaine for Postoperative Pain in Children Undergoing Tonsillectomies: A Double-Blinded, Randomized, Placebo-Controlled Trial.",
      "reported_at": "2026-07-03T09:46:01.554974"
    },
    "42002501": {
      "title": "Selected 2025 Highlights in Congenital Cardiac Anesthesia.",
      "reported_at": "2026-07-03T09:46:01.554974"
    },
    "41963151": {
      "title": "Rethinking Lactate in Cardiac Surgery and Intensive Care.",
      "reported_at": "2026-07-03T09:46:01.554974"
    },
    "41785463": {
      "title": "Prospective Study of Postoperative Respiratory Depression Metrics After Cesarean Delivery Among Women Receiving Intrathecal Morphine.",
      "reported_at": "2026-07-03T09:46:01.554974"
    },
    "42360449": {
      "title": "Antepartum hemoglobin concentrations and postpartum patient-reported outcomes: a retrospective study.",
      "reported_at": "2026-07-03T09:46:01.554974"
    },
    "42384869": {
      "title": "Adjuvant Pembrolizumab plus Belzutifan for Renal-Cell Carcinoma.",
      "reported_at": "2026-07-04T08:14:21.898708"
    },
    "42384870": {
      "title": "Rituximab versus Ocrelizumab in Newly Diagnosed Relapsing Multiple Sclerosis.",
      "reported_at": "2026-07-04T08:14:21.898708"
    },
    "42251856": {
      "title": "Cagrilintide-semaglutide (CagriSema) as an add-on to basal insulin in adults with type 2 diabetes (REIMAGINE 3): a randomised, double-blind, placebo-controlled, multicentre, phase 3 study.",
      "reported_at": "2026-07-04T08:14:21.898708"
    },
    "42367140": {
      "title": "Psychometric Evaluation of the Japanese Version of the Hospital Survey on Patient Safety Culture 2.0 (J-HSOPS 2.0): A Nationwide Cross-sectional Study.",
      "reported_at": "2026-07-04T08:14:21.898708"
    },
    "42214392": {
      "title": "Sacituzumab tirumotecan plus pembrolizumab versus pembrolizumab in PD-L1-positive advanced non-small-cell lung cancer (OptiTROP-Lung05): interim analysis of a randomised, open-label, phase 3 trial.",
      "reported_at": "2026-07-04T08:14:21.898708"
    },
    "42025562": {
      "title": "Airway ultrasound in anaesthesia training: a scoping review.",
      "reported_at": "2026-07-05T08:33:06.490421"
    },
    "41334974": {
      "title": "The impact of coaching on professional identity development in postgraduate medical trainees: A scoping review.",
      "reported_at": "2026-07-05T08:33:06.490421"
    },
    "41196008": {
      "title": "Myths of contestation in the medical education curriculum: A dialogical exploration.",
      "reported_at": "2026-07-05T08:33:06.490421"
    },
    "41486829": {
      "title": "Final-year students' perspectives on socially responsive curricula in medical education: A qualitative case study.",
      "reported_at": "2026-07-05T08:33:06.490421"
    },
    "41950401": {
      "title": "Feasibility Pilot Trial for the Trajectories of Recovery after Intravenous Propofol versus Inhaled Volatile Anesthesia (THRIVE) Pragmatic Randomized Clinical Trial.",
      "reported_at": "2026-07-06T12:29:24.391998"
    },
    "42210709": {
      "title": "Secondary Analysis of the CAN-Study, a Randomised Controlled Trial - Local Anaesthesia and Overall Survival.",
      "reported_at": "2026-07-06T12:29:24.391998"
    },
    "42097956": {
      "title": "The environmental footprint and ecotoxicity of sevoflurane and propofol anaesthesia: a retrospective observational modelling study.",
      "reported_at": "2026-07-06T12:29:24.391998"
    },
    "41632715": {
      "title": "Feasibility of a Multicomponent Protocol to Promote Dreaming during Surgical Anesthesia.",
      "reported_at": "2026-07-06T12:29:24.391998"
    },
    "42089120": {
      "title": "Combined Transversus Abdominis Plane and Rectus Sheath Blocks in Open Inguinal Hernia Repair: Protocol for a Double-Blind Randomized Controlled Trial (PRO-RSTAP).",
      "reported_at": "2026-07-06T12:29:24.391998"
    },
    "42126304": {
      "title": "Ultrasound-Guided Superficial Parasternal Intercostal Plane Block for Early Pain Management in Patients Undergoing Cardiac Surgery-A Randomized Controlled Trial.",
      "reported_at": "2026-07-07T10:35:21.094006"
    },
    "40015722": {
      "title": "Use and safety of corticosteroid injections in joints and musculoskeletal soft tissue: guidelines from the American Society of Regional Anesthesia and Pain Medicine, the American Academy of Pain Medicine, the American Society of Interventional Pain Physicians, and the International Pain and Spine Intervention Society.",
      "reported_at": "2026-07-07T10:35:21.094006"
    },
    "40055004": {
      "title": "Comparison of femoral triangle plus iPACK blocks with femoral triangle block alone for anterior cruciate ligament reconstruction: a randomized controlled clinical trial on postoperative pain and knee function.",
      "reported_at": "2026-07-07T10:35:21.094006"
    },
    "41405684": {
      "title": "Effect of Goal-Directed Intraoperative Blood Pressure Management on Postoperative Delirium in Older Patients Undergoing Hip Fracture Surgery: A Randomized Controlled Trial.",
      "reported_at": "2026-07-07T10:35:21.094006"
    },
    "40169358": {
      "title": "Baby steps to mastery: building blocks for novices in pediatric regional anesthesia.",
      "reported_at": "2026-07-07T10:35:21.094006"
    },
    "40000247": {
      "title": "Factors associated with poor pain experience after surgery.",
      "reported_at": "2026-07-08T06:46:46.107756"
    },
    "42225440": {
      "title": "Postoperative hypotension in patients recovering from noncardiac surgery: a prospective, blinded observational study.",
      "reported_at": "2026-07-08T06:46:46.107756"
    },
    "41815001": {
      "title": "Pulmonary complications with individualised vs. fixed positive end-expiratory pressure in older patients recovering from lung cancer surgery: a randomised trial.",
      "reported_at": "2026-07-08T06:46:46.107756"
    },
    "41816950": {
      "title": "Quality of care received by children with suspected appendicitis in the UK National Health Service.",
      "reported_at": "2026-07-08T06:46:46.107756"
    },
    "42083722": {
      "title": "An Observational Study of Changes in Renin Concentrations and Associations With Complications Following Cardiac Surgery.",
      "reported_at": "2026-07-08T06:46:46.107756"
    },
    "42405450": {
      "title": "Management of major thoracic trauma: a narrative review.",
      "reported_at": "2026-07-09T10:34:00.653030"
    },
    "42412219": {
      "title": "Lung- and diaphragm-protective mechanical ventilation in acute respiratory distress syndrome.",
      "reported_at": "2026-07-09T10:34:00.653030"
    },
    "42412218": {
      "title": "60 years of ARDS and the evolution of extracorporeal lung support - from ECMO to ECCO<sub>2</sub>R.",
      "reported_at": "2026-07-09T10:34:00.653030"
    },
    "42418776": {
      "title": "Nutrition Therapy in Critically Ill Adults.",
      "reported_at": "2026-07-09T10:34:00.653030"
    },
    "42285120": {
      "title": "Diagnosis and treatment of postpartum haemorrhage: a race against time.",
      "reported_at": "2026-07-09T10:34:00.653030"
    },
    "42418775": {
      "title": "Ensartinib in Resected <i>ALK</i>-Positive Non-Small-Cell Lung Cancer.",
      "reported_at": "2026-07-11T06:27:25.559763"
    },
    "42418774": {
      "title": "Setmelanotide for the Treatment of Acquired Hypothalamic Obesity.",
      "reported_at": "2026-07-11T06:27:25.559763"
    },
    "41812190": {
      "title": "Inhaled Treprostinil for Idiopathic Pulmonary Fibrosis.",
      "reported_at": "2026-07-11T06:27:25.559763"
    },
    "42259339": {
      "title": "Orforglipron compared with dapagliflozin in adults with type 2 diabetes and inadequate glycaemic control with metformin (ACHIEVE-2): a multicentre, randomised, non-inferiority, open-label, phase 3 trial.",
      "reported_at": "2026-07-11T06:27:25.559763"
    },
    "42397249": {
      "title": "Impact of Nursing Leadership for Surgical Excellence Program on Perioperative Care and Patient Safety in Low-Income Countries: A Mixed-Methods Study.",
      "reported_at": "2026-07-11T06:27:25.559763"
    },
    "42018768": {
      "title": "A Population-based Cross-sectional Analysis of Extended-release Opioid Dispensing Incidence, Prognostic Factors, and Variation after Total Joint Arthroplasty.",
      "reported_at": "2026-07-13T08:39:06.534702"
    },
    "40096994": {
      "title": "Accuracy of patient-reported opioid use to verified prescription fills before and after surgery.",
      "reported_at": "2026-07-13T08:39:06.534702"
    },
    "42425794": {
      "title": "Regional anaesthesia and chronic postsurgical pain: a systematic review and network meta-analysis.",
      "reported_at": "2026-07-13T08:39:06.534702"
    },
    "39971386": {
      "title": "Perineuromal hydrodissection for acute postamputation pain? An observational study in a time of war.",
      "reported_at": "2026-07-13T08:39:06.534702"
    },
    "42414111": {
      "title": "Effects of fentanyl on diaphragm muscle force in patients undergoing knee arthroplasty: a randomised double-blind clinical trial.",
      "reported_at": "2026-07-13T08:39:06.534702"
    },
    "42425793": {
      "title": "Comparison of intrathecal morphine, lateral quadratus lumborum block, and their combination for analgesia and quality of recovery after Caesarean delivery: a randomised, double-blind, two-centre clinical trial.",
      "reported_at": "2026-07-14T06:23:08.006148"
    },
    "42406517": {
      "title": "Phrenic-sparing strategies for shoulder surgery: balancing respiratory safety and block completeness.",
      "reported_at": "2026-07-14T06:23:08.006148"
    },
    "42425699": {
      "title": "Evaluating the effectiveness of bilateral erector spinae plane blocks in addition to standard multimodal analgesia at reducing opioid consumption in patients undergoing elective mammoplasty in an ambulatory surgical center: a randomized clinical trial.",
      "reported_at": "2026-07-14T06:23:08.006148"
    }
  }
}